{
  "technologies": [
    {
      "name": "React",
      "icon": "react",
      "color": "#61DAFB",
      "description": "A JavaScript library for building user interfaces with a declarative, component-based approach",
      "url": "https://react.dev"
    },
    {
      "name": "Next.js",
      "icon": "nextjs",
      "color": "#8A2BE2",
      "description": "The React framework for production-grade applications with hybrid static & server rendering",
      "url": "https://nextjs.org"
    },
    {
      "name": "TypeScript",
      "icon": "typescript",
      "color": "#3178C6",
      "description": "A strongly typed programming language that builds on JavaScript with static type definitions",
      "url": "https://www.typescriptlang.org"
    },
    {
      "name": "WordPress",
      "icon": "wordpress",
      "color": "#21759B",
      "description": "Open-source content management system for building websites and blogs",
      "url": "https://wordpress.org"
    },
    {
      "name": "Figma",
      "icon": "figma",
      "color": "#F8A79E",
      "description": "A collaborative interface design tool for creating UI/UX designs and prototypes",
      "url": "https://www.figma.com"
    },
    {
      "name": "Git",
      "icon": "git",
      "color": "#F05032",
      "description": "Free and open source distributed version control system designed for speed and efficiency",
      "url": "https://git-scm.com"
    },
    {
      "name": "GitHub",
      "icon": "github",
      "color": "#181717",
      "description": "Web-based platform for version control and collaboration using Git",
      "url": "https://github.com"
    },
    {
      "name": "AWS",
      "icon": "aws",
      "color": "#FF9900",
      "description": "Amazon Web Services provides on-demand cloud computing platforms and APIs",
      "url": "https://aws.amazon.com"
    },
    {
      "name": "DigitalOcean",
      "icon": "digitalocean",
      "color": "#0080FF",
      "description": "Cloud infrastructure provider for deploying and scaling applications",
      "url": "https://www.digitalocean.com"
    }
  ]
}
